{
	"$schema": "https://vega.github.io/schema/vega/v5.json",
	"background": "#ffffff",
	"padding": 20,
	"autosize": "pad",	
	"data": [
		{
			"name": "source",
			"values": [
				{
					"Outcome": "1",
					"Score1": "-0.307687115774605",
					"Score2": "2.05235645004595"
				},
				{
					"Outcome": "1",
					"Score1": "1.3377996192471",
					"Score2": "4.60557960364248"
				},
				{
					"Outcome": "1",
					"Score1": "-0.734593617795476",
					"Score2": "0.426714801591562"
				},
				{
					"Outcome": "0",
					"Score1": "6.82503963376793",
					"Score2": "-2.97120209919155"
				},
				{
					"Outcome": "1",
					"Score1": "-1.61712179144781",
					"Score2": "7.73188410721637"
				},
				{
					"Outcome": "0",
					"Score1": "-2.4956687132838",
					"Score2": "-4.32808575130052"
				},
				{
					"Outcome": "0",
					"Score1": "-2.85836108277166",
					"Score2": "-3.66650977150631"
				},
				{
					"Outcome": "1",
					"Score1": "-1.04669227189899",
					"Score2": "-1.69505220873678"
				},
				{
					"Outcome": "0",
					"Score1": "6.30433591200739",
					"Score2": "0.183732475020159"
				},
				{
					"Outcome": "1",
					"Score1": "-4.65884772766698",
					"Score2": "-1.1505263181099"
				},
				{
					"Outcome": "1",
					"Score1": "-6.79698556613182",
					"Score2": "-2.07438146406691"
				},
				{
					"Outcome": "0",
					"Score1": "-4.69187476573495",
					"Score2": "7.66461246860344"
				},
				{
					"Outcome": "0",
					"Score1": "-3.3473957355895",
					"Score2": "4.03117751812666"
				},
				{
					"Outcome": "1",
					"Score1": "-2.38002709883273",
					"Score2": "7.17553578394272"
				},
				{
					"Outcome": "1",
					"Score1": "-4.16855721188673",
					"Score2": "5.57749867139881"
				},
				{
					"Outcome": "1",
					"Score1": "-2.76193352251651",
					"Score2": "4.98070803482801"
				},
				{
					"Outcome": "1",
					"Score1": "3.44982781113236",
					"Score2": "2.77022846042929"
				},
				{
					"Outcome": "0",
					"Score1": "-1.47318019965446",
					"Score2": "-7.620126987108"
				},
				{
					"Outcome": "1",
					"Score1": "-3.96585522560645",
					"Score2": "-3.53377509698618"
				},
				{
					"Outcome": "1",
					"Score1": "2.74656642318995",
					"Score2": "2.55471839290228"
				},
				{
					"Outcome": "0",
					"Score1": "3.66903725026706",
					"Score2": "-2.60458375689806"
				},
				{
					"Outcome": "0",
					"Score1": "6.95403042300911",
					"Score2": "-1.21604580351902"
				},
				{
					"Outcome": "0",
					"Score1": "3.35022737059714",
					"Score2": "-5.44459984154136"
				},
				{
					"Outcome": "0",
					"Score1": "5.74101438535088",
					"Score2": "-1.07008134167097"
				},
				{
					"Outcome": "0",
					"Score1": "2.53067400582464",
					"Score2": "-7.2005342142221"
				},
				{
					"Outcome": "0",
					"Score1": "6.09492427187256",
					"Score2": "7.13133590145278"
				},
				{
					"Outcome": "1",
					"Score1": "-0.526526831831142",
					"Score2": "-2.04311989650225"
				},
				{
					"Outcome": "1",
					"Score1": "-1.78658761398021",
					"Score2": "-2.39221557272953"
				},
				{
					"Outcome": "0",
					"Score1": "-1.62048752572939",
					"Score2": "-5.19783954878882"
				},
				{
					"Outcome": "1",
					"Score1": "0.121640506300064",
					"Score2": "1.95029228750491"
				},
				{
					"Outcome": "1",
					"Score1": "0.388583047974693",
					"Score2": "6.97272783399644"
				},
				{
					"Outcome": "0",
					"Score1": "4.51478352396487",
					"Score2": "-1.17489538195039"
				},
				{
					"Outcome": "1",
					"Score1": "-2.03752250372235",
					"Score2": "-1.53137169975211"
				},
				{
					"Outcome": "1",
					"Score1": "-2.95530968724034",
					"Score2": "-3.13222074631105"
				},
				{
					"Outcome": "0",
					"Score1": "-2.52639513979406",
					"Score2": "-3.39951284754586"
				},
				{
					"Outcome": "0",
					"Score1": "26.4496920649649",
					"Score2": "-5.92163612625051"
				},
				{
					"Outcome": "1",
					"Score1": "-4.34821943628712",
					"Score2": "-2.25847675595513"
				},
				{
					"Outcome": "1",
					"Score1": "1.29226695931311",
					"Score2": "2.35291582303857"
				},
				{
					"Outcome": "1",
					"Score1": "-1.90478063104101",
					"Score2": "-3.47541889099351"
				},
				{
					"Outcome": "1",
					"Score1": "5.00345663986748",
					"Score2": "-6.04107839214846"
				},
				{
					"Outcome": "0",
					"Score1": "3.04981807019279",
					"Score2": "4.21636747327274"
				},
				{
					"Outcome": "0",
					"Score1": "-4.58171367829802",
					"Score2": "0.240853906698805"
				},
				{
					"Outcome": "0",
					"Score1": "-3.72438191496197",
					"Score2": "-4.80403844434178"
				},
				{
					"Outcome": "0",
					"Score1": "-1.38613904579597",
					"Score2": "-2.20090689556974"
				},
				{
					"Outcome": "0",
					"Score1": "1.39627274778572",
					"Score2": "-3.41774950420696"
				},
				{
					"Outcome": "1",
					"Score1": "-1.77297146314745",
					"Score2": "-0.358346682749692"
				},
				{
					"Outcome": "0",
					"Score1": "-8.46275689275702",
					"Score2": "-3.63033818798029"
				},
				{
					"Outcome": "0",
					"Score1": "-7.23851860582136",
					"Score2": "1.33393911519587"
				},
				{
					"Outcome": "0",
					"Score1": "0.136218251865346",
					"Score2": "-4.89031324537244"
				},
				{
					"Outcome": "1",
					"Score1": "-1.13688012635075",
					"Score2": "2.6131396913978"
				},
				{
					"Outcome": "1",
					"Score1": "0.462813056996124",
					"Score2": "4.83583361657827"
				},
				{
					"Outcome": "0",
					"Score1": "6.50613344608297",
					"Score2": "-7.04137442234926"
				},
				{
					"Outcome": "0",
					"Score1": "2.11978209885975",
					"Score2": "-5.04473189602363"
				},
				{
					"Outcome": "0",
					"Score1": "-3.70068437536105",
					"Score2": "-0.260332697650686"
				},
				{
					"Outcome": "0",
					"Score1": "1.27470663259211",
					"Score2": "1.93184117865639"
				},
				{
					"Outcome": "0",
					"Score1": "-4.56680722807761",
					"Score2": "-3.42251212141911"
				},
				{
					"Outcome": "0",
					"Score1": "-1.62221759042903",
					"Score2": "-8.0902951347472"
				},
				{
					"Outcome": "0",
					"Score1": "0.63555427117174",
					"Score2": "-5.48863893194357"
				},
				{
					"Outcome": "0",
					"Score1": "-0.271739320021514",
					"Score2": "6.77186418685949"
				},
				{
					"Outcome": "0",
					"Score1": "-5.83189809737642",
					"Score2": "-6.09857663599421"
				},
				{
					"Outcome": "1",
					"Score1": "2.04290398431977",
					"Score2": "-0.270629350200099"
				},
				{
					"Outcome": "1",
					"Score1": "-0.227188971573867",
					"Score2": "4.87156382757026"
				},
				{
					"Outcome": "1",
					"Score1": "-0.0786900293989252",
					"Score2": "2.09557691789567"
				},
				{
					"Outcome": "0",
					"Score1": "-4.86007202446321",
					"Score2": "-1.34755915622987"
				},
				{
					"Outcome": "0",
					"Score1": "-2.93476870152056",
					"Score2": "-4.39475599614432"
				},
				{
					"Outcome": "1",
					"Score1": "0.450389395985706",
					"Score2": "-2.38790985921781"
				},
				{
					"Outcome": "0",
					"Score1": "0.848343963074046",
					"Score2": "-4.99272409253583"
				},
				{
					"Outcome": "1",
					"Score1": "-2.42311287889304",
					"Score2": "-4.13397417702326"
				},
				{
					"Outcome": "0",
					"Score1": "-1.40370416472462",
					"Score2": "-6.20946025773374"
				},
				{
					"Outcome": "0",
					"Score1": "-1.598792701561",
					"Score2": "4.67236900988027"
				},
				{
					"Outcome": "0",
					"Score1": "0.603671949547943",
					"Score2": "-6.45445725240077"
				},
				{
					"Outcome": "1",
					"Score1": "1.19768316774319",
					"Score2": "8.20217760982441"
				},
				{
					"Outcome": "0",
					"Score1": "4.19822228475546",
					"Score2": "-1.11089062567779"
				},
				{
					"Outcome": "0",
					"Score1": "4.61588851738345",
					"Score2": "3.84079120923222"
				},
				{
					"Outcome": "0",
					"Score1": "-2.44583304387548",
					"Score2": "-6.0767000163523"
				},
				{
					"Outcome": "1",
					"Score1": "-3.6647673375645",
					"Score2": "4.55195462841907"
				},
				{
					"Outcome": "0",
					"Score1": "-4.70112236902769",
					"Score2": "-1.60227589170985"
				},
				{
					"Outcome": "0",
					"Score1": "-5.32489471279565",
					"Score2": "9.84874173204101"
				},
				{
					"Outcome": "1",
					"Score1": "9.1009857233457",
					"Score2": "2.27240269641592"
				},
				{
					"Outcome": "0",
					"Score1": "-0.0547772468548582",
					"Score2": "1.65109824835547"
				},
				{
					"Outcome": "1",
					"Score1": "-0.992502810861582",
					"Score2": "10.1861784722937"
				},
				{
					"Outcome": "0",
					"Score1": "-3.72937865066789",
					"Score2": "3.47341654134728"
				},
				{
					"Outcome": "0",
					"Score1": "-2.31415255995341",
					"Score2": "-2.57014528517736"
				},
				{
					"Outcome": "0",
					"Score1": "-1.34765333373428",
					"Score2": "-3.52460014780503"
				},
				{
					"Outcome": "0",
					"Score1": "3.00344372920725",
					"Score2": "-4.67171967356502"
				},
				{
					"Outcome": "0",
					"Score1": "-2.04530730372056",
					"Score2": "-0.267858732554612"
				},
				{
					"Outcome": "0",
					"Score1": "-4.8103502017629",
					"Score2": "5.73118351394097"
				},
				{
					"Outcome": "0",
					"Score1": "1.31501596182414",
					"Score2": "3.44221285342339"
				},
				{
					"Outcome": "0",
					"Score1": "3.1931515953087",
					"Score2": "2.24440746458904"
				},
				{
					"Outcome": "1",
					"Score1": "-2.17382518156473",
					"Score2": "0.0322439211466127"
				},
				{
					"Outcome": "0",
					"Score1": "0.812264990407364",
					"Score2": "2.33668421500727"
				},
				{
					"Outcome": "0",
					"Score1": "0.127586553112305",
					"Score2": "-0.813021135626467"
				},
				{
					"Outcome": "1",
					"Score1": "-0.781133174846643",
					"Score2": "-1.20902418770456"
				},
				{
					"Outcome": "0",
					"Score1": "2.03253693724777",
					"Score2": "0.419185130415315"
				},
				{
					"Outcome": "0",
					"Score1": "4.90283764462747",
					"Score2": "-3.54239073803068"
				},
				{
					"Outcome": "0",
					"Score1": "-1.8792764230733",
					"Score2": "14.1037633055657"
				},
				{
					"Outcome": "0",
					"Score1": "-0.0808479484036859",
					"Score2": "-4.64773107683749"
				},
				{
					"Outcome": "0",
					"Score1": "-1.0027586030771",
					"Score2": "4.65459165597749"
				},
				{
					"Outcome": "1",
					"Score1": "0.191294823174041",
					"Score2": "11.0077064450139"
				},
				{
					"Outcome": "0",
					"Score1": "-5.03542876765778",
					"Score2": "-9.18203619909785"
				},
				{
					"Outcome": "0",
					"Score1": "-2.70942872571744",
					"Score2": "-3.49484118799483"
				},
				{
					"Outcome": "1",
					"Score1": "-1.36345950577161",
					"Score2": "-0.833117301308368"
				},
				{
					"Outcome": "0",
					"Score1": "-3.97871561340883",
					"Score2": "12.9683607985423"
				},
				{
					"Outcome": "1",
					"Score1": "14.529641346529",
					"Score2": "1.1713419047031"
				},
				{
					"Outcome": "0",
					"Score1": "-1.9386538212135",
					"Score2": "3.04887629859906"
				},
				{
					"Outcome": "0",
					"Score1": "-0.0942136562345882",
					"Score2": "1.56792432291964"
				},
				{
					"Outcome": "0",
					"Score1": "12.8449390396456",
					"Score2": "1.92201111059404"
				},
				{
					"Outcome": "0",
					"Score1": "2.93612978710286",
					"Score2": "-0.793353961050958"
				}
			]
		},
		{
			"name": "density",
			"source": "source",
			"transform": [
				{
					"type": "kde2d",
					"groupby": [
						"Outcome"
					],
					"size": [
						{
							"signal": "width"
						},
						{
							"signal": "height"
						}
					],
					"x": {
						"expr": "scale('x', datum.Score1)"
					},
					"y": {
						"expr": "scale('y', datum.Score2)"
					},
					"bandwidth": {
						"signal": "[-1, -1]"
					},
					"counts": true
				}
			]
		},
		{
			"name": "contours",
			"source": "density",
			"transform": [
				{
					"type": "isocontour",
					"field": "grid",
					"resolve": "shared",
					"levels": 10
				}
			]
		}
	],
	"legends": [
		{
			"stroke": "color",
			"symbolType": "stroke"
		}
	],
	"marks": [
		{
			"name": "mark",
			"type": "symbol",
			"tooltip": true,
			"from": {
				"data": "source"
			},
			"encode": {
				"enter": {
						"tooltip": {
							"signal": "datum"
						}
					},
				"update": {
					"x": {
						"scale": "x",
						"field": "Score1"
					},
					"y": {
						"scale": "y",
						"field": "Score2"
					},
					"shape": {
						"value": "circle"
					},
					"strokeWidth": {
						"value": 2
					},
					"opacity": {
						"value": 0.5
					},
					"stroke": {
						"scale": "color",
						"field": "Outcome"
					},
					"fill": {
						"value": "transparent"
					}
				}
			}
		},
		{
			"type": "path",
			"clip": true,
			"from": {
				"data": "contours"
			},
			"encode": {
				"enter": {
					"strokeWidth": {
						"value": 1
					},
					"strokeOpacity": {
						"value": 1
					},
					"stroke": {
						"scale": "color",
						"field": "Outcome"
					}
				}
			},
			"transform": [
				{
					"type": "geopath",
					"field": "datum.contour"
				}
			]
		}
	],
	"scales": [
		{
			"name": "x",
			"type": "linear",
			"round": true,
			"nice": true,
			"zero": true,
			"domain": {
				"data": "source",
				"field": "Score1"
			},
			"range": "width"
		},
		{
			"name": "y",
			"type": "linear",
			"round": true,
			"nice": true,
			"zero": true,
			"domain": {
				"data": "source",
				"field": "Score2"
			},
			"range": "height"
		},
		{
			"name": "color",
			"type": "ordinal",
			"domain": {
				"data": "source",
				"field": "Outcome",
				"sort": {
					"order": "descending"
				}
			},
			"range": "category"
		}
	],
	"axes": [
		{
			"scale": "x",
			"grid": true,
			"domain": false,
			"orient": "bottom",
			"tickCount": 5
		},
		{
			"scale": "y",
			"grid": true,
			"domain": false,
			"orient": "left",
			"tickCount": 5,
			"titlePadding": 5
		}
	]
}